jacksonquery/__init__.py
jacksonquery/classification_schema.py
jacksonquery/fee_extractor.py
jacksonquery/file_parser.py
jacksonquery/returns_extractor.py
jacksonquery/source_extractor.py
jacksonquery/stats_extractor.py
jacksonquery/tenure_extractor.py
jacksonquery/turnover_extractor.py
portfolio_optimization/__init__.py
portfolio_optimization/benchmark_model.py
portfolio_optimization/factor_data.py
portfolio_optimization/factor_model.py
portfolio_optimization/optimization_config.py
portfolio_optimization/optimization_data.py
portfolio_optimization/optimization_inputs.py
portfolio_optimization/optimization_model.py
portfolio_optimization/performance.py
JacksonQuery-0.0.1.dist-info/METADATA
JacksonQuery-0.0.1.dist-info/WHEEL
JacksonQuery-0.0.1.dist-info/top_level.txt
JacksonQuery-0.0.1.dist-info/RECORD
